{"version":"d27d7978f1b8","generated_at":"2026-07-21T23:54:22.777Z","store":{"row":417,"store_code":"0673","store_name":"KM 광주충장NC점","region":"전남지역"},"orders":[{"source_no":"10717","source_flag":"F","order_no":"2026072072390641","line_no":1,"store_code":"0673","store_name":"KM 광주충장NC점","sale_type":"판매","brand":"CROCS","product_name":"OFF COURT CLOG","style_code":"CRS208371","color":"BLACK","size":"270","quantity":1,"stock_quantity":1,"regular_price":74900,"sale_amount":39000,"shipping_type":"매장","status":"출고","store_transfer_status":"","registered_at":"2026-07-20T15:00:00.000Z","shipped_at":"2026-07-21T04:47:31.000Z","shipped_by":"김수인","settled_at":null,"settled_by":"","sales_date":null,"pos_no":"","transaction_no":""},{"source_no":"10718","source_flag":"F","order_no":"2026072073225721","line_no":2,"store_code":"0673","store_name":"KM 광주충장NC점","sale_type":"판매","brand":"PUMA","product_name":"SPEEDCAT GO V INF","style_code":"PKI40843402","color":"For All Time Red-PUMA White-PUMA Black","size":"140","quantity":1,"stock_quantity":3,"regular_price":69000,"sale_amount":69000,"shipping_type":"매장","status":"출고","store_transfer_status":"","registered_at":"2026-07-20T15:00:00.000Z","shipped_at":"2026-07-21T01:42:35.000Z","shipped_by":"김수인","settled_at":null,"settled_by":"","sales_date":null,"pos_no":"","transaction_no":""},{"source_no":"10719","source_flag":"F","order_no":"2026072121761711","line_no":3,"store_code":"0673","store_name":"KM 광주충장NC점","sale_type":"판매","brand":"CROCS","product_name":"OFF COURT CLOG","style_code":"CRS208371","color":"NAVY","size":"265","quantity":1,"stock_quantity":2,"regular_price":74900,"sale_amount":39000,"shipping_type":"타매장 요청","status":"출고","store_transfer_status":"점입확정","registered_at":"2026-07-20T15:00:00.000Z","shipped_at":"2026-07-21T06:40:09.000Z","shipped_by":"김수인","settled_at":null,"settled_by":"","sales_date":null,"pos_no":"","transaction_no":""},{"source_no":"10720","source_flag":"F","order_no":"2026072133420751","line_no":4,"store_code":"0673","store_name":"KM 광주충장NC점","sale_type":"판매","brand":"PUMA","product_name":"SPEEDCAT GO V INF","style_code":"PKI40843402","color":"For All Time Red-PUMA White-PUMA Black","size":"160","quantity":1,"stock_quantity":1,"regular_price":69000,"sale_amount":69000,"shipping_type":"매장","status":"출고","store_transfer_status":"","registered_at":"2026-07-20T15:00:00.000Z","shipped_at":"2026-07-21T11:39:56.000Z","shipped_by":"김수인","settled_at":null,"settled_by":"","sales_date":null,"pos_no":"","transaction_no":""},{"source_no":"10721","source_flag":"F","order_no":"2026072133420761","line_no":5,"store_code":"0673","store_name":"KM 광주충장NC점","sale_type":"판매","brand":"PUMA","product_name":"SPEEDCAT GO V INF","style_code":"PKI40843401","color":"PUMA Black-PUMA White","size":"120","quantity":1,"stock_quantity":1,"regular_price":69000,"sale_amount":69000,"shipping_type":"백화점","status":"출고","store_transfer_status":"","registered_at":"2026-07-20T15:00:00.000Z","shipped_at":"2026-07-21T11:39:56.000Z","shipped_by":"김수인","settled_at":null,"settled_by":"","sales_date":null,"pos_no":"","transaction_no":""},{"source_no":"10722","source_flag":"F","order_no":"2026071879443251","line_no":1,"store_code":"0673","store_name":"KM 광주충장NC점","sale_type":"판매","brand":"PUMA","product_name":"SPEEDCAT GO V INF","style_code":"PKI40843401","color":"PUMA Black-PUMA White","size":"140","quantity":1,"stock_quantity":1,"regular_price":69000,"sale_amount":69000,"shipping_type":"매장","status":"출고","store_transfer_status":"","registered_at":"2026-07-18T15:00:00.000Z","shipped_at":"2026-07-19T09:23:23.000Z","shipped_by":"김수인","settled_at":null,"settled_by":"","sales_date":null,"pos_no":"","transaction_no":""},{"source_no":"10723","source_flag":"F","order_no":"2026071881627351","line_no":2,"store_code":"0673","store_name":"KM 광주충장NC점","sale_type":"판매","brand":"CROCS","product_name":"OFF COURT CLOG","style_code":"CRS208371","color":"BLACK","size":"250","quantity":1,"stock_quantity":1,"regular_price":74900,"sale_amount":39000,"shipping_type":"타매장 요청","status":"출고","store_transfer_status":"점입확정","registered_at":"2026-07-18T15:00:00.000Z","shipped_at":"2026-07-19T01:18:14.000Z","shipped_by":"김수인","settled_at":null,"settled_by":"","sales_date":null,"pos_no":"","transaction_no":""},{"source_no":"10724","source_flag":"F","order_no":"2026071889590961","line_no":3,"store_code":"0673","store_name":"KM 광주충장NC점","sale_type":"판매","brand":"PUMA","product_name":"SPEEDCAT GO V INF","style_code":"PKI40843402","color":"For All Time Red-PUMA White-PUMA Black","size":"140","quantity":1,"stock_quantity":3,"regular_price":69000,"sale_amount":69000,"shipping_type":"매장","status":"출고","store_transfer_status":"","registered_at":"2026-07-18T15:00:00.000Z","shipped_at":"2026-07-19T09:22:42.000Z","shipped_by":"김수인","settled_at":null,"settled_by":"","sales_date":null,"pos_no":"","transaction_no":""},{"source_no":"10725","source_flag":"F","order_no":"2026071898133701","line_no":4,"store_code":"0673","store_name":"KM 광주충장NC점","sale_type":"판매","brand":"PUMA","product_name":"SPEEDCAT GO V INF","style_code":"PKI40843401","color":"PUMA Black-PUMA White","size":"150","quantity":1,"stock_quantity":3,"regular_price":69000,"sale_amount":69000,"shipping_type":"타매장 요청","status":"출고","store_transfer_status":"점입확정","registered_at":"2026-07-18T15:00:00.000Z","shipped_at":"2026-07-19T01:33:00.000Z","shipped_by":"김수인","settled_at":null,"settled_by":"","sales_date":null,"pos_no":"","transaction_no":""},{"source_no":"10726","source_flag":"F","order_no":"2026071914378771","line_no":5,"store_code":"0673","store_name":"KM 광주충장NC점","sale_type":"판매","brand":"PUMA","product_name":"SPEEDCAT GO V INF","style_code":"PKI40843402","color":"For All Time Red-PUMA White-PUMA Black","size":"140","quantity":1,"stock_quantity":3,"regular_price":69000,"sale_amount":69000,"shipping_type":"타매장 요청","status":"출고","store_transfer_status":"점입확정","registered_at":"2026-07-18T15:00:00.000Z","shipped_at":"2026-07-19T10:10:01.000Z","shipped_by":"김수인","settled_at":null,"settled_by":"","sales_date":null,"pos_no":"","transaction_no":""},{"source_no":"10729","source_flag":"F","order_no":"2026071121123651","line_no":8,"store_code":"0673","store_name":"KM 광주충장NC점","sale_type":"판매","brand":"PUMA","product_name":"SPEEDCAT GO V INF","style_code":"PKI40843402","color":"For All Time Red-PUMA White-PUMA Black","size":"150","quantity":1,"stock_quantity":3,"regular_price":69000,"sale_amount":69000,"shipping_type":"매장","status":"출고","store_transfer_status":"","registered_at":"2026-07-18T15:00:00.000Z","shipped_at":"2026-07-19T05:57:13.000Z","shipped_by":"김수인","settled_at":null,"settled_by":"","sales_date":null,"pos_no":"","transaction_no":""},{"source_no":"10730","source_flag":"F","order_no":"2026071746626871","line_no":1,"store_code":"0673","store_name":"KM 광주충장NC점","sale_type":"판매","brand":"CROCS","product_name":"OFF COURT CLOG","style_code":"CRS208371","color":"NAVY","size":"260","quantity":1,"stock_quantity":1,"regular_price":74900,"sale_amount":39000,"shipping_type":"매장","status":"출고","store_transfer_status":"","registered_at":"2026-07-16T15:00:00.000Z","shipped_at":"2026-07-17T01:59:07.000Z","shipped_by":"김수인","settled_at":null,"settled_by":"","sales_date":null,"pos_no":"","transaction_no":""},{"source_no":"10731","source_flag":"F","order_no":"2026071453320281","line_no":1,"store_code":"0673","store_name":"KM 광주충장NC점","sale_type":"판매","brand":"PUMA","product_name":"SPEEDCAT GO V INF","style_code":"PKI40843401","color":"PUMA Black-PUMA White","size":"140","quantity":1,"stock_quantity":1,"regular_price":69000,"sale_amount":69000,"shipping_type":"매장","status":"출고","store_transfer_status":"","registered_at":"2026-07-14T15:00:00.000Z","shipped_at":"2026-07-15T02:50:14.000Z","shipped_by":"김수인","settled_at":null,"settled_by":"","sales_date":null,"pos_no":"","transaction_no":""},{"source_no":"10748","source_flag":"F","order_no":"2026071048547871","line_no":2,"store_code":"0673","store_name":"KM 광주충장NC점","sale_type":"판매","brand":"PUMA","product_name":"SPEEDCAT GO V INF","style_code":"PKI40843402","color":"For All Time Red-PUMA White-PUMA Black","size":"140","quantity":1,"stock_quantity":3,"regular_price":69000,"sale_amount":69000,"shipping_type":"매장","status":"출고","store_transfer_status":"","registered_at":"2026-07-09T15:00:00.000Z","shipped_at":"2026-07-10T01:55:55.000Z","shipped_by":"김수인","settled_at":null,"settled_by":"","sales_date":null,"pos_no":"","transaction_no":""},{"source_no":"10733","source_flag":"F","order_no":"2026070893286201","line_no":3,"store_code":"0673","store_name":"KM 광주충장NC점","sale_type":"판매","brand":"PUMA","product_name":"SPEEDCAT GO V INF","style_code":"PKI40843402","color":"For All Time Red-PUMA White-PUMA Black","size":"130","quantity":1,"stock_quantity":2,"regular_price":69000,"sale_amount":69000,"shipping_type":"매장","status":"출고","store_transfer_status":"","registered_at":"2026-07-14T15:00:00.000Z","shipped_at":"2026-07-15T08:50:38.000Z","shipped_by":"김수인","settled_at":null,"settled_by":"","sales_date":null,"pos_no":"","transaction_no":""},{"source_no":"10734","source_flag":"F","order_no":"2026071576190941","line_no":4,"store_code":"0673","store_name":"KM 광주충장NC점","sale_type":"판매","brand":"PUMA","product_name":"SPEEDCAT GO V INF","style_code":"PKI40843402","color":"For All Time Red-PUMA White-PUMA Black","size":"140","quantity":1,"stock_quantity":3,"regular_price":69000,"sale_amount":69000,"shipping_type":"매장","status":"출고","store_transfer_status":"","registered_at":"2026-07-14T15:00:00.000Z","shipped_at":"2026-07-15T08:56:52.000Z","shipped_by":"김수인","settled_at":null,"settled_by":"","sales_date":null,"pos_no":"","transaction_no":""},{"source_no":"10735","source_flag":"F","order_no":"2026071576190941","line_no":5,"store_code":"0673","store_name":"KM 광주충장NC점","sale_type":"판매","brand":"PUMA","product_name":"SPEEDCAT GO V INF","style_code":"PKI40843402","color":"For All Time Red-PUMA White-PUMA Black","size":"140","quantity":1,"stock_quantity":3,"regular_price":69000,"sale_amount":69000,"shipping_type":"백화점","status":"출고","store_transfer_status":"","registered_at":"2026-07-14T15:00:00.000Z","shipped_at":"2026-07-15T08:56:57.000Z","shipped_by":"김수인","settled_at":null,"settled_by":"","sales_date":null,"pos_no":"","transaction_no":""},{"source_no":"10737","source_flag":"F","order_no":"2026071358886511","line_no":1,"store_code":"0673","store_name":"KM 광주충장NC점","sale_type":"판매","brand":"CROCS","product_name":"OFF COURT CLOG","style_code":"CRS208371","color":"BLACK","size":"290","quantity":1,"stock_quantity":1,"regular_price":74900,"sale_amount":39000,"shipping_type":"타매장 요청","status":"출고","store_transfer_status":"점입확정","registered_at":"2026-07-12T15:00:00.000Z","shipped_at":"2026-07-13T01:17:05.000Z","shipped_by":"김수인","settled_at":null,"settled_by":"","sales_date":null,"pos_no":"","transaction_no":""},{"source_no":"10738","source_flag":"F","order_no":"2026071359742761","line_no":2,"store_code":"0673","store_name":"KM 광주충장NC점","sale_type":"판매","brand":"PUMA","product_name":"SPEEDCAT GO V PS","style_code":"PKI40843301","color":"PUMA Black-PUMA White","size":"180","quantity":1,"stock_quantity":1,"regular_price":79000,"sale_amount":79000,"shipping_type":"매장","status":"출고","store_transfer_status":"","registered_at":"2026-07-12T15:00:00.000Z","shipped_at":"2026-07-13T01:44:11.000Z","shipped_by":"김수인","settled_at":null,"settled_by":"","sales_date":null,"pos_no":"","transaction_no":""},{"source_no":"10741","source_flag":"F","order_no":"2026070610049851","line_no":6,"store_code":"0673","store_name":"KM 광주충장NC점","sale_type":"판매","brand":"CROCS","product_name":"OFF COURT CLOG","style_code":"CRS208371","color":"NAVY","size":"265","quantity":1,"stock_quantity":2,"regular_price":74900,"sale_amount":39000,"shipping_type":"매장","status":"출고","store_transfer_status":"","registered_at":"2026-07-12T15:00:00.000Z","shipped_at":"2026-07-13T11:45:43.000Z","shipped_by":"김수인","settled_at":null,"settled_by":"","sales_date":null,"pos_no":"","transaction_no":""},{"source_no":"10743","source_flag":"F","order_no":"2026071121123651","line_no":2,"store_code":"0673","store_name":"KM 광주충장NC점","sale_type":"판매","brand":"PUMA","product_name":"SPEEDCAT GO V INF","style_code":"PKI40843402","color":"For All Time Red-PUMA White-PUMA Black","size":"140","quantity":1,"stock_quantity":3,"regular_price":69000,"sale_amount":69000,"shipping_type":"타매장 요청","status":"출고","store_transfer_status":"점입확정","registered_at":"2026-07-11T15:00:00.000Z","shipped_at":"2026-07-12T10:12:20.000Z","shipped_by":"김수인","settled_at":null,"settled_by":"","sales_date":null,"pos_no":"","transaction_no":""},{"source_no":"10749","source_flag":"F","order_no":"2026070524815961","line_no":3,"store_code":"0673","store_name":"KM 광주충장NC점","sale_type":"판매","brand":"PUMA","product_name":"SPEEDCAT GO V INF","style_code":"PKI40843402","color":"For All Time Red-PUMA White-PUMA Black","size":"120","quantity":1,"stock_quantity":1,"regular_price":69000,"sale_amount":69000,"shipping_type":"매장","status":"출고","store_transfer_status":"","registered_at":"2026-07-09T15:00:00.000Z","shipped_at":"2026-07-10T09:05:06.000Z","shipped_by":"김수인","settled_at":null,"settled_by":"","sales_date":null,"pos_no":"","transaction_no":""},{"source_no":"10750","source_flag":"F","order_no":"13101528587398","line_no":4,"store_code":"0673","store_name":"KM 광주충장NC점","sale_type":"판매","brand":"HAWKINS","product_name":"RAIN BOOTS(15-21)","style_code":"HK92019","color":"DINOSAUR","size":"190","quantity":1,"stock_quantity":1,"regular_price":29000,"sale_amount":19000,"shipping_type":"매장","status":"출고","store_transfer_status":"","registered_at":"2026-07-09T15:00:00.000Z","shipped_at":"2026-07-11T03:49:53.000Z","shipped_by":"김수인","settled_at":null,"settled_by":"","sales_date":null,"pos_no":"","transaction_no":""},{"source_no":"10752","source_flag":"F","order_no":"2026071078609451","line_no":6,"store_code":"0673","store_name":"KM 광주충장NC점","sale_type":"판매","brand":"PUMA","product_name":"SPEEDCAT GO V INF","style_code":"PKI40843402","color":"For All Time Red-PUMA White-PUMA Black","size":"130","quantity":1,"stock_quantity":2,"regular_price":69000,"sale_amount":69000,"shipping_type":"타매장 요청","status":"출고","store_transfer_status":"점입확정","registered_at":"2026-07-09T15:00:00.000Z","shipped_at":"2026-07-11T09:45:29.000Z","shipped_by":"김수인","settled_at":null,"settled_by":"","sales_date":null,"pos_no":"","transaction_no":""},{"source_no":"10753","source_flag":"F","order_no":"24101488102296","line_no":1,"store_code":"0673","store_name":"KM 광주충장NC점","sale_type":"판매","brand":"HAWKINS","product_name":"RAIN BOOTS(15-21)","style_code":"HK92019","color":"DINOSAUR","size":"180","quantity":1,"stock_quantity":3,"regular_price":29000,"sale_amount":19000,"shipping_type":"매장","status":"출고","store_transfer_status":"","registered_at":"2026-07-08T15:00:00.000Z","shipped_at":"2026-07-09T03:02:40.000Z","shipped_by":"김수인","settled_at":null,"settled_by":"","sales_date":null,"pos_no":"","transaction_no":""},{"source_no":"10756","source_flag":"F","order_no":"2026070893286201","line_no":4,"store_code":"0673","store_name":"KM 광주충장NC점","sale_type":"판매","brand":"PUMA","product_name":"SPEEDCAT GO V INF","style_code":"PKI40843402","color":"For All Time Red-PUMA White-PUMA Black","size":"140","quantity":1,"stock_quantity":3,"regular_price":69000,"sale_amount":69000,"shipping_type":"매장","status":"출고","store_transfer_status":"","registered_at":"2026-07-08T15:00:00.000Z","shipped_at":"2026-07-09T04:05:42.000Z","shipped_by":"김수인","settled_at":null,"settled_by":"","sales_date":null,"pos_no":"","transaction_no":""},{"source_no":"10761","source_flag":"F","order_no":"2026070610049851","line_no":1,"store_code":"0673","store_name":"KM 광주충장NC점","sale_type":"판매","brand":"CROCS","product_name":"OFF COURT CLOG","style_code":"CRS208371","color":"NAVY","size":"260","quantity":1,"stock_quantity":1,"regular_price":74900,"sale_amount":39000,"shipping_type":"매장","status":"출고","store_transfer_status":"","registered_at":"2026-07-06T15:00:00.000Z","shipped_at":"2026-07-07T02:17:16.000Z","shipped_by":"김수인","settled_at":null,"settled_by":"","sales_date":null,"pos_no":"","transaction_no":""},{"source_no":"10785","source_flag":"F","order_no":"2026070556463901","line_no":3,"store_code":"0673","store_name":"KM 광주충장NC점","sale_type":"판매","brand":"PUMA","product_name":"SPEEDCAT GO V INF","style_code":"PKI40843401","color":"PUMA Black-PUMA White","size":"150","quantity":1,"stock_quantity":3,"regular_price":69000,"sale_amount":69000,"shipping_type":"타매장 요청","status":"출고","store_transfer_status":"점입확정","registered_at":"2026-07-05T15:00:00.000Z","shipped_at":"2026-07-06T02:25:29.000Z","shipped_by":"김수인","settled_at":null,"settled_by":"","sales_date":null,"pos_no":"","transaction_no":""},{"source_no":"10787","source_flag":"F","order_no":"2026070661005651","line_no":6,"store_code":"0673","store_name":"KM 광주충장NC점","sale_type":"판매","brand":"PUMA","product_name":"SPEEDCAT GO V INF","style_code":"PKI40843402","color":"For All Time Red-PUMA White-PUMA Black","size":"160","quantity":1,"stock_quantity":1,"regular_price":69000,"sale_amount":69000,"shipping_type":"백화점","status":"출고","store_transfer_status":"","registered_at":"2026-07-05T15:00:00.000Z","shipped_at":"2026-07-06T02:18:29.000Z","shipped_by":"김수인","settled_at":null,"settled_by":"","sales_date":null,"pos_no":"","transaction_no":""},{"source_no":"10797","source_flag":"F","order_no":"2026070519200971","line_no":8,"store_code":"0673","store_name":"KM 광주충장NC점","sale_type":"판매","brand":"PUMA","product_name":"SPEEDCAT GO V INF","style_code":"PKI40843402","color":"For All Time Red-PUMA White-PUMA Black","size":"140","quantity":1,"stock_quantity":3,"regular_price":69000,"sale_amount":69000,"shipping_type":"매장","status":"출고","store_transfer_status":"","registered_at":"2026-07-04T15:00:00.000Z","shipped_at":"2026-07-06T02:17:43.000Z","shipped_by":"김수인","settled_at":null,"settled_by":"","sales_date":null,"pos_no":"","transaction_no":""},{"source_no":"10803","source_flag":"F","order_no":"2026070370714981","line_no":2,"store_code":"0673","store_name":"KM 광주충장NC점","sale_type":"판매","brand":"PUMA","product_name":"SPEEDCAT GO V INF","style_code":"PKI40843402","color":"For All Time Red-PUMA White-PUMA Black","size":"130","quantity":1,"stock_quantity":2,"regular_price":69000,"sale_amount":69000,"shipping_type":"매장","status":"출고","store_transfer_status":"","registered_at":"2026-07-03T15:00:00.000Z","shipped_at":"2026-07-04T05:46:15.000Z","shipped_by":"김수인","settled_at":null,"settled_by":"","sales_date":null,"pos_no":"","transaction_no":""},{"source_no":"10804","source_flag":"F","order_no":"2026070370714991","line_no":3,"store_code":"0673","store_name":"KM 광주충장NC점","sale_type":"판매","brand":"PUMA","product_name":"SPEEDCAT GO V INF","style_code":"PKI40843401","color":"PUMA Black-PUMA White","size":"140","quantity":1,"stock_quantity":1,"regular_price":69000,"sale_amount":69000,"shipping_type":"매장","status":"출고","store_transfer_status":"","registered_at":"2026-07-03T15:00:00.000Z","shipped_at":"2026-07-04T05:46:15.000Z","shipped_by":"김수인","settled_at":null,"settled_by":"","sales_date":null,"pos_no":"","transaction_no":""}]}