{"version":"d27d7978f1b8","generated_at":"2026-07-21T23:54:22.777Z","store":{"row":314,"store_code":"0549","store_name":"GS 광양LF몰점","region":"전남지역"},"orders":[{"source_no":"1395","source_flag":"F","order_no":"2026072087559381","line_no":2,"store_code":"0549","store_name":"GS 광양LF몰점","sale_type":"판매","brand":"LACOSTE","product_name":"CLUB-LOW","style_code":"7-49SFA0043","color":"WHT/DK GRN","size":"225","quantity":1,"stock_quantity":1,"regular_price":159000,"sale_amount":69000,"shipping_type":"타매장 요청","status":"출고","store_transfer_status":"점입확정","registered_at":"2026-07-20T15:00:00.000Z","shipped_at":"2026-07-21T01:02:32.000Z","shipped_by":"김소현","settled_at":null,"settled_by":"","sales_date":null,"pos_no":"","transaction_no":""},{"source_no":"1396","source_flag":"F","order_no":"2026072084633981","line_no":3,"store_code":"0549","store_name":"GS 광양LF몰점","sale_type":"판매","brand":"CROCS","product_name":"CLASSIC FROSTED CLOG","style_code":"CRS210928","color":"PURPLE MOON","size":"265","quantity":1,"stock_quantity":0,"regular_price":69900,"sale_amount":48900,"shipping_type":"타매장 요청","status":"등록","store_transfer_status":"","registered_at":"2026-07-20T15:00:00.000Z","shipped_at":null,"shipped_by":"","settled_at":null,"settled_by":"","sales_date":null,"pos_no":"","transaction_no":""},{"source_no":"1397","source_flag":"F","order_no":"2026072080575741","line_no":4,"store_code":"0549","store_name":"GS 광양LF몰점","sale_type":"판매","brand":"PUMA","product_name":"ROYALCAT COMFORT 2 ESSENTIA","style_code":"PKI40428103","color":"PUMA Black-Cool Dark Gray","size":"260","quantity":1,"stock_quantity":1,"regular_price":39000,"sale_amount":31000,"shipping_type":"타매장 요청","status":"출고","store_transfer_status":"점입확정","registered_at":"2026-07-20T15:00:00.000Z","shipped_at":"2026-07-21T01:03:01.000Z","shipped_by":"김소현","settled_at":null,"settled_by":"","sales_date":null,"pos_no":"","transaction_no":""},{"source_no":"1398","source_flag":"F","order_no":"2026072079725641","line_no":5,"store_code":"0549","store_name":"GS 광양LF몰점","sale_type":"판매","brand":"PUMA","product_name":"SPEEDCAT MULE WNS","style_code":"PKI40961804","color":"Espresso Bean-Haute Coffee","size":"250","quantity":1,"stock_quantity":1,"regular_price":129000,"sale_amount":129000,"shipping_type":"타매장 요청","status":"출고","store_transfer_status":"점입확정","registered_at":"2026-07-20T15:00:00.000Z","shipped_at":"2026-07-21T01:03:14.000Z","shipped_by":"김소현","settled_at":null,"settled_by":"","sales_date":null,"pos_no":"","transaction_no":""},{"source_no":"1399","source_flag":"F","order_no":"2026072123345541","line_no":6,"store_code":"0549","store_name":"GS 광양LF몰점","sale_type":"판매","brand":"CROCS","product_name":"CLASSIC BAE CLOG W","style_code":"CRS206302","color":"BLACK","size":"230","quantity":1,"stock_quantity":4,"regular_price":99900,"sale_amount":99900,"shipping_type":"타매장 요청","status":"출고","store_transfer_status":"점입확정","registered_at":"2026-07-20T15:00:00.000Z","shipped_at":"2026-07-21T07:39:59.000Z","shipped_by":"김소현","settled_at":null,"settled_by":"","sales_date":null,"pos_no":"","transaction_no":""},{"source_no":"1400","source_flag":"F","order_no":"2026072128041231","line_no":7,"store_code":"0549","store_name":"GS 광양LF몰점","sale_type":"판매","brand":"ADIDAS","product_name":"GAZELLE","style_code":"JR6288","color":"ORBGRN/FOCOLI/GOLDMT","size":"275","quantity":1,"stock_quantity":0,"regular_price":139000,"sale_amount":69000,"shipping_type":"타매장 요청","status":"출고","store_transfer_status":"전표등록","registered_at":"2026-07-20T15:00:00.000Z","shipped_at":"2026-07-21T09:03:25.000Z","shipped_by":"김소현","settled_at":null,"settled_by":"","sales_date":null,"pos_no":"","transaction_no":""},{"source_no":"1401","source_flag":"F","order_no":"2026072126556501","line_no":8,"store_code":"0549","store_name":"GS 광양LF몰점","sale_type":"판매","brand":"LACOSTE","product_name":"CLUB-LOW","style_code":"7-49SFA0120","color":"WHT/WHT","size":"235","quantity":1,"stock_quantity":1,"regular_price":149000,"sale_amount":69000,"shipping_type":"타매장 요청","status":"출고","store_transfer_status":"전표등록","registered_at":"2026-07-20T15:00:00.000Z","shipped_at":"2026-07-21T11:29:12.000Z","shipped_by":"김소현","settled_at":null,"settled_by":"","sales_date":null,"pos_no":"","transaction_no":""},{"source_no":"1402","source_flag":"F","order_no":"2026072052958031","line_no":1,"store_code":"0549","store_name":"GS 광양LF몰점","sale_type":"판매","brand":"ADIDAS","product_name":"SAMBA JANE W","style_code":"KI2775","color":"SANPIN/CREWHT/GUM3","size":"220","quantity":1,"stock_quantity":1,"regular_price":149000,"sale_amount":104000,"shipping_type":"매장","status":"출고","store_transfer_status":"","registered_at":"2026-07-19T15:00:00.000Z","shipped_at":"2026-07-20T01:32:20.000Z","shipped_by":"김소현","settled_at":null,"settled_by":"","sales_date":null,"pos_no":"","transaction_no":""},{"source_no":"1403","source_flag":"F","order_no":"2026072068652131","line_no":3,"store_code":"0549","store_name":"GS 광양LF몰점","sale_type":"판매","brand":"LACOSTE","product_name":"STORM 96 2K LITE","style_code":"7-50SFA0181","color":"OFF WHT/DK PURP","size":"245","quantity":1,"stock_quantity":1,"regular_price":129000,"sale_amount":69000,"shipping_type":"타매장 요청","status":"출고","store_transfer_status":"점입확정","registered_at":"2026-07-19T15:00:00.000Z","shipped_at":"2026-07-21T04:19:05.000Z","shipped_by":"김소현","settled_at":null,"settled_by":"","sales_date":null,"pos_no":"","transaction_no":""},{"source_no":"1404","source_flag":"F","order_no":"2026072056339391","line_no":4,"store_code":"0549","store_name":"GS 광양LF몰점","sale_type":"판매","brand":"LACOSTE","product_name":"BACKSLAM","style_code":"7-49CMA0035","color":"OFF WHT/LT TAN","size":"265","quantity":1,"stock_quantity":2,"regular_price":129000,"sale_amount":59000,"shipping_type":"타매장 요청","status":"출고","store_transfer_status":"점입확정","registered_at":"2026-07-19T15:00:00.000Z","shipped_at":"2026-07-20T10:13:10.000Z","shipped_by":"김소현","settled_at":null,"settled_by":"","sales_date":null,"pos_no":"","transaction_no":""},{"source_no":"1405","source_flag":"F","order_no":"2026071914119851","line_no":4,"store_code":"0549","store_name":"GS 광양LF몰점","sale_type":"판매","brand":"CROCS","product_name":"CLASSIC BAE CLOG W","style_code":"CRS206302","color":"BLACK","size":"230","quantity":1,"stock_quantity":4,"regular_price":99900,"sale_amount":99900,"shipping_type":"매장","status":"출고","store_transfer_status":"","registered_at":"2026-07-18T15:00:00.000Z","shipped_at":"2026-07-19T01:16:26.000Z","shipped_by":"김소현","settled_at":null,"settled_by":"","sales_date":null,"pos_no":"","transaction_no":""},{"source_no":"1406","source_flag":"F","order_no":"2026071918637551","line_no":5,"store_code":"0549","store_name":"GS 광양LF몰점","sale_type":"판매","brand":"CROCS","product_name":"CLASSIC BAE CLOG W","style_code":"CRS206302","color":"BLACK","size":"230","quantity":1,"stock_quantity":4,"regular_price":99900,"sale_amount":99900,"shipping_type":"타매장 요청","status":"출고","store_transfer_status":"점입확정","registered_at":"2026-07-18T15:00:00.000Z","shipped_at":"2026-07-19T01:35:05.000Z","shipped_by":"김소현","settled_at":null,"settled_by":"","sales_date":null,"pos_no":"","transaction_no":""},{"source_no":"1407","source_flag":"F","order_no":"2026071927564211","line_no":6,"store_code":"0549","store_name":"GS 광양LF몰점","sale_type":"판매","brand":"CROCS","product_name":"GETAWAY STRAPPY","style_code":"CRS209587","color":"BLACK","size":"230","quantity":1,"stock_quantity":1,"regular_price":54900,"sale_amount":43000,"shipping_type":"타매장 요청","status":"출고","store_transfer_status":"점입확정","registered_at":"2026-07-18T15:00:00.000Z","shipped_at":"2026-07-19T10:02:03.000Z","shipped_by":"김소현","settled_at":null,"settled_by":"","sales_date":null,"pos_no":"","transaction_no":""},{"source_no":"1408","source_flag":"F","order_no":"2026071924725271","line_no":7,"store_code":"0549","store_name":"GS 광양LF몰점","sale_type":"판매","brand":"CROCS","product_name":"CLASSIC BAE CLOG W","style_code":"CRS206302","color":"BLACK","size":"230","quantity":1,"stock_quantity":4,"regular_price":99900,"sale_amount":99900,"shipping_type":"매장","status":"출고","store_transfer_status":"","registered_at":"2026-07-18T15:00:00.000Z","shipped_at":"2026-07-19T10:01:28.000Z","shipped_by":"김소현","settled_at":null,"settled_by":"","sales_date":null,"pos_no":"","transaction_no":""},{"source_no":"1409","source_flag":"F","order_no":"2026071931995621","line_no":10,"store_code":"0549","store_name":"GS 광양LF몰점","sale_type":"판매","brand":"CROCS","product_name":"CLASSIC PLATFORM CLOG W","style_code":"CRS206750","color":"BONE","size":"230","quantity":1,"stock_quantity":2,"regular_price":79900,"sale_amount":79900,"shipping_type":"매장","status":"출고","store_transfer_status":"","registered_at":"2026-07-18T15:00:00.000Z","shipped_at":"2026-07-19T11:06:34.000Z","shipped_by":"김소현","settled_at":null,"settled_by":"","sales_date":null,"pos_no":"","transaction_no":""},{"source_no":"1410","source_flag":"F","order_no":"2026071879643231","line_no":1,"store_code":"0549","store_name":"GS 광양LF몰점","sale_type":"판매","brand":"LACOSTE","product_name":"AURA","style_code":"7-50SMA0154","color":"BLK/OFF WHT","size":"270","quantity":1,"stock_quantity":2,"regular_price":169000,"sale_amount":101000,"shipping_type":"타매장 요청","status":"출고","store_transfer_status":"점입확정","registered_at":"2026-07-17T15:00:00.000Z","shipped_at":"2026-07-18T01:45:59.000Z","shipped_by":"김소현","settled_at":null,"settled_by":"","sales_date":null,"pos_no":"","transaction_no":""},{"source_no":"1411","source_flag":"F","order_no":"2026071879643221","line_no":2,"store_code":"0549","store_name":"GS 광양LF몰점","sale_type":"판매","brand":"LACOSTE","product_name":"COURT SET","style_code":"7-50SMA0223","color":"BLK/WHT","size":"270","quantity":1,"stock_quantity":2,"regular_price":169000,"sale_amount":99000,"shipping_type":"매장","status":"출고","store_transfer_status":"","registered_at":"2026-07-17T15:00:00.000Z","shipped_at":"2026-07-18T01:46:19.000Z","shipped_by":"김소현","settled_at":null,"settled_by":"","sales_date":null,"pos_no":"","transaction_no":""},{"source_no":"1412","source_flag":"F","order_no":"2026071745905681","line_no":1,"store_code":"0549","store_name":"GS 광양LF몰점","sale_type":"판매","brand":"CROCS","product_name":"CLASSIC BAE CLOG W","style_code":"CRS206302","color":"BLACK","size":"220","quantity":1,"stock_quantity":2,"regular_price":99900,"sale_amount":99900,"shipping_type":"타매장 요청","status":"출고","store_transfer_status":"점입확정","registered_at":"2026-07-16T15:00:00.000Z","shipped_at":"2026-07-17T08:28:09.000Z","shipped_by":"김소현","settled_at":null,"settled_by":"","sales_date":null,"pos_no":"","transaction_no":""},{"source_no":"1413","source_flag":"F","order_no":"2026071598648161","line_no":1,"store_code":"0549","store_name":"GS 광양LF몰점","sale_type":"판매","brand":"LACOSTE","product_name":"CARNABY SET","style_code":"7-50SMA0062","color":"BLK/BLK","size":"280","quantity":1,"stock_quantity":2,"regular_price":159000,"sale_amount":111000,"shipping_type":"타매장 요청","status":"출고","store_transfer_status":"점입확정","registered_at":"2026-07-15T15:00:00.000Z","shipped_at":"2026-07-16T01:19:22.000Z","shipped_by":"김소현","settled_at":null,"settled_by":"","sales_date":null,"pos_no":"","transaction_no":""},{"source_no":"1414","source_flag":"F","order_no":"2026071620007711","line_no":2,"store_code":"0549","store_name":"GS 광양LF몰점","sale_type":"판매","brand":"CROCS","product_name":"CLASSIC PLATFORM CLOG W","style_code":"CRS206750","color":"BONE","size":"240","quantity":1,"stock_quantity":3,"regular_price":79900,"sale_amount":79900,"shipping_type":"매장","status":"출고","store_transfer_status":"","registered_at":"2026-07-15T15:00:00.000Z","shipped_at":"2026-07-16T02:15:40.000Z","shipped_by":"김소현","settled_at":null,"settled_by":"","sales_date":null,"pos_no":"","transaction_no":""},{"source_no":"1415","source_flag":"F","order_no":"2026071623740571","line_no":3,"store_code":"0549","store_name":"GS 광양LF몰점","sale_type":"판매","brand":"LACOSTE","product_name":"CLUB-LOW","style_code":"7-49SMA0042","color":"WHT/DK GRN","size":"250","quantity":1,"stock_quantity":1,"regular_price":159000,"sale_amount":69000,"shipping_type":"타매장 요청","status":"출고","store_transfer_status":"점입확정","registered_at":"2026-07-15T15:00:00.000Z","shipped_at":"2026-07-16T04:56:02.000Z","shipped_by":"김소현","settled_at":null,"settled_by":"","sales_date":null,"pos_no":"","transaction_no":""},{"source_no":"1418","source_flag":"F","order_no":"2026071435432491","line_no":3,"store_code":"0549","store_name":"GS 광양LF몰점","sale_type":"판매","brand":"LACOSTE","product_name":"CLUB-LOW","style_code":"7-49SFA0120","color":"WHT/WHT","size":"235","quantity":1,"stock_quantity":1,"regular_price":149000,"sale_amount":69000,"shipping_type":"타매장 요청","status":"출고","store_transfer_status":"점입확정","registered_at":"2026-07-14T15:00:00.000Z","shipped_at":"2026-07-15T01:03:33.000Z","shipped_by":"김소현","settled_at":null,"settled_by":"","sales_date":null,"pos_no":"","transaction_no":""},{"source_no":"1420","source_flag":"F","order_no":"2026071421352241","line_no":1,"store_code":"0549","store_name":"GS 광양LF몰점","sale_type":"판매","brand":"LACOSTE","product_name":"CLUB-LOW","style_code":"7-49SMA0042","color":"BLK/OFF WHT","size":"250","quantity":1,"stock_quantity":1,"regular_price":159000,"sale_amount":69000,"shipping_type":"매장","status":"출고","store_transfer_status":"","registered_at":"2026-07-13T15:00:00.000Z","shipped_at":"2026-07-14T02:34:13.000Z","shipped_by":"김소현","settled_at":null,"settled_by":"","sales_date":null,"pos_no":"","transaction_no":""},{"source_no":"1421","source_flag":"F","order_no":"2026071417219821","line_no":2,"store_code":"0549","store_name":"GS 광양LF몰점","sale_type":"판매","brand":"CROCS","product_name":"CLASSIC BAE CLOG W","style_code":"CRS206302","color":"BLACK","size":"220","quantity":1,"stock_quantity":2,"regular_price":99900,"sale_amount":99900,"shipping_type":"매장","status":"출고","store_transfer_status":"","registered_at":"2026-07-13T15:00:00.000Z","shipped_at":"2026-07-14T02:30:22.000Z","shipped_by":"김소현","settled_at":null,"settled_by":"","sales_date":null,"pos_no":"","transaction_no":""},{"source_no":"1428","source_flag":"F","order_no":"2026071123336791","line_no":1,"store_code":"0549","store_name":"GS 광양LF몰점","sale_type":"판매","brand":"PUMA","product_name":"SPEEDCAT MULE WNS","style_code":"PKI40961804","color":"Espresso Bean-Haute Coffee","size":"255","quantity":1,"stock_quantity":1,"regular_price":129000,"sale_amount":129000,"shipping_type":"타매장 요청","status":"출고","store_transfer_status":"점입확정","registered_at":"2026-07-11T15:00:00.000Z","shipped_at":"2026-07-13T01:06:55.000Z","shipped_by":"김소현","settled_at":null,"settled_by":"","sales_date":null,"pos_no":"","transaction_no":""},{"source_no":"1432","source_flag":"F","order_no":"2026071243445221","line_no":8,"store_code":"0549","store_name":"GS 광양LF몰점","sale_type":"판매","brand":"LACOSTE","product_name":"CLUB-LOW","style_code":"7-49SMA0042","color":"WHT/DK GRN","size":"275","quantity":1,"stock_quantity":1,"regular_price":159000,"sale_amount":69000,"shipping_type":"타매장 요청","status":"출고","store_transfer_status":"점입확정","registered_at":"2026-07-11T15:00:00.000Z","shipped_at":"2026-07-13T01:37:13.000Z","shipped_by":"김소현","settled_at":null,"settled_by":"","sales_date":null,"pos_no":"","transaction_no":""},{"source_no":"1435","source_flag":"F","order_no":"2026071049841451","line_no":1,"store_code":"0549","store_name":"GS 광양LF몰점","sale_type":"판매","brand":"LACOSTE","product_name":"CLUB-LOW","style_code":"7-49SMA0042","color":"WHT/DK GRN","size":"280","quantity":1,"stock_quantity":1,"regular_price":159000,"sale_amount":69000,"shipping_type":"타매장 요청","status":"출고","store_transfer_status":"점입확정","registered_at":"2026-07-09T15:00:00.000Z","shipped_at":"2026-07-10T01:19:06.000Z","shipped_by":"김소현","settled_at":null,"settled_by":"","sales_date":null,"pos_no":"","transaction_no":""}]}